pomf/__init__.py
pomf/pomf.py
pomf-0.6.dist-info/DESCRIPTION.rst
pomf-0.6.dist-info/METADATA
pomf-0.6.dist-info/RECORD
pomf-0.6.dist-info/WHEEL
pomf-0.6.dist-info/metadata.json
pomf-0.6.dist-info/top_level.txt
