Metadata-Version: 2.0
Name: pomf
Version: 0.6
Summary: Pomf.se clone uploader
Home-page: https://github.com/AggressivelyMeows/Pomf.py
Author: Cerulean
Author-email: cerulean.connor@gmail.com
License: UNKNOWN
Platform: UNKNOWN
Classifier: Programming Language :: Python :: 3
Classifier: License :: OSI Approved :: MIT License
Classifier: Operating System :: OS Independent
